modian_setup.py
setup.py
conda/meta.yaml
modian/__init__.py
modian/bn2smv.py
modian/bnutils.py
modian/models.py
modian/setup.py
modian/utils.py
modian.egg-info/PKG-INFO
modian.egg-info/SOURCES.txt
modian.egg-info/dependency_links.txt
modian.egg-info/requires.txt
modian.egg-info/top_level.txt